tinesight/__init__.py
tinesight/_api.py
tinesight/client.py
tinesight/registrar.py
tinesight-0.0.11.dev1.dist-info/WHEEL
tinesight-0.0.11.dev1.dist-info/METADATA
tinesight-0.0.11.dev1.dist-info/RECORD
