Metadata-Version: 2.3
Name: tinesight
Version: 0.0.11.dev1
Summary: Tinesight SDK
Requires-Dist: cryptography>=46.0.3
Requires-Dist: pycognito>=2024.5.1
Requires-Dist: opencv-python>=4.13.0.90 ; extra == 'video'
Requires-Python: >=3.12
Provides-Extra: video
